AUTHORS
CHANGES
LICENSE
MANIFEST.in
README.rst
setup.py
manwe/__init__.py
manwe/commands.py
manwe/config.py
manwe/default_config.py
manwe/errors.py
manwe/fields.py
manwe/resources.py
manwe/session.py
manwe.egg-info/PKG-INFO
manwe.egg-info/SOURCES.txt
manwe.egg-info/dependency_links.txt
manwe.egg-info/entry_points.txt
manwe.egg-info/pbr.json
manwe.egg-info/requires.txt
manwe.egg-info/top_level.txt