Metadata-Version: 1.1
Name: manwe
Version: 1.2.0
Summary: A Python client library and command line interface to the Varda database for genomic variation frequencies
Home-page: https://github.com/varda/manwe
Author: Martijn Vermaat
Author-email: martijn@vermaat.name
License: MIT License
Keywords: bioinformatics
Platform: any
Classifier: Development Status :: 3 - Alpha
Classifier: Intended Audience :: Developers
Classifier: Intended Audience :: Science/Research
Classifier: Operating System :: OS Independent
Classifier: Programming Language :: Python
Classifier: Topic :: Scientific/Engineering
